mbonig/rds_tools/__init__.py
mbonig/rds_tools/py.typed
mbonig/rds_tools/_jsii/__init__.py
mbonig/rds_tools/_jsii/rds-tools@2.1.0.jsii.tgz
mbonig_rds_tools-2.1.0.dist-info/LICENSE
mbonig_rds_tools-2.1.0.dist-info/METADATA
mbonig_rds_tools-2.1.0.dist-info/WHEEL
mbonig_rds_tools-2.1.0.dist-info/top_level.txt
mbonig_rds_tools-2.1.0.dist-info/RECORD
